chutils/__init__.py
chutils/config.py
chutils/decorators.py
chutils/logger.py
chutils/secret_manager.py
chutils-2.4.0.dist-info/licenses/LICENSE
chutils-2.4.0.dist-info/METADATA
chutils-2.4.0.dist-info/WHEEL
chutils-2.4.0.dist-info/RECORD
