Metadata-Version: 2.4
Name: chutils
Version: 2.4.0
Summary: Набор простых и удобных утилит для Python, который избавляет от рутины при работе с конфигурацией и логированием в новых проектах.
License: MIT
License-File: LICENSE
Author: Chu4hel
Author-email: sergeiivanov636@gmail.com
Requires-Python: >=3.9, !=2.7.*, !=3.0.*, !=3.1.*, !=3.2.*, !=3.3.*, !=3.4.*, !=3.5.*, !=3.6.*, !=3.7.*, !=3.8.*
Classifier: License :: OSI Approved :: MIT License
Classifier: Programming Language :: Python :: 3
Classifier: Programming Language :: Python :: 3.10
Classifier: Programming Language :: Python :: 3.11
Classifier: Programming Language :: Python :: 3.12
Classifier: Programming Language :: Python :: 3.13
Classifier: Programming Language :: Python :: 3.14
Requires-Dist: dotenv (>=0.9.9,<0.10.0)
Requires-Dist: keyring (>=25.7.0,<26.0.0)
Requires-Dist: python-dotenv (>=1.2.1,<2.0.0)
Requires-Dist: pyyaml (>=6.0.3,<7.0.0)
